<?xml version="1.0" encoding="utf-8"?>
<totalinfo>
  <controls>
    <controlentry>
      <control>
        <name>ddlStatusGraphics</name>
        <windowcaption>Status Graphics</windowcaption>
        <description>Specifies a graphic set used to indicate KPI values.</description>
        <memberlist>PivotGridFieldBase.KPIGraphic</memberlist>
        <dtimage/>
      </control>
    </controlentry>

    <controlentry>
      <control>
        <name>ddlTrendGraphics</name>
        <windowcaption>Trend Graphics</windowcaption>
        <description>Specifies a graphic set used to indicate KPI values.</description>
        <memberlist>PivotGridFieldBase.KPIGraphic</memberlist>
        <dtimage/>
      </control>
    </controlentry>
  </controls>
</totalinfo>